LICENSE
MANIFEST.in
NEWS.rst
README.rst
setup.py
django_sampledatahelper.egg-info/PKG-INFO
django_sampledatahelper.egg-info/SOURCES.txt
django_sampledatahelper.egg-info/dependency_links.txt
django_sampledatahelper.egg-info/requires.txt
django_sampledatahelper.egg-info/top_level.txt
sampledatahelper/__init__.py
sampledatahelper/compat.py
sampledatahelper/handlers.py
sampledatahelper/helper.py
sampledatahelper/model_helper.py
sampledatahelper/register.py
sampledatahelper/management/__init__.py
sampledatahelper/management/commands/__init__.py
sampledatahelper/management/commands/sampledatafiller.py