Metadata-Version: 1.1
Name: django-sampledatahelper
Version: 0.5
Summary: Helper class for generate sampledata
Home-page: https://github.com/kaleidos/django-sampledatahelper
Author: Jesús Espino García
Author-email: jespinog@gmail.com
License: BSD
Keywords: django,data,example
Platform: UNKNOWN
Classifier: Programming Language :: Python
Classifier: Development Status :: 4 - Beta
Classifier: Framework :: Django
Classifier: Intended Audience :: Developers
Classifier: License :: OSI Approved :: BSD License
Classifier: Operating System :: OS Independent
Classifier: Programming Language :: Python
Classifier: Topic :: Internet :: WWW/HTTP
